Lab3/dmem/dmem.sv
/* ********************************************
 *	COSE222 Lab #3
 *
 *	Module: data memory (dmem.sv)
 *	- 1 address input port
 *	- 32-bit 1 data input and output ports
 *	- A single entry size is 32-bit
 *
 *	Author: Gunjae Koo (gunjaekoo@korea.ac.kr)
 *
 * ********************************************
 */

`timescale 1ns/1ps
`define FF 1    // Flip-flop delay for just better waveform view

module dmem
#(  parameter DMEM_DEPTH = 1024,    // dmem depth (default: 1024 entries = 4 KB)
              DMEM_ADDR_WIDTH = 10 )
(
    input           clk,
    input   [DMEM_ADDR_WIDTH-1:0]   addr,
    input   [31:0]  din,
    input           mem_read,
    input           mem_write,
    output  [31:0]  dout
);

    /* Data memory does not receive the clock signal in the textbook.
     * Without clock we need to implement the data memory with latches.
     * However, you must avoid generating latches in real RTL design.
     * If latches are generated after synthesis, then it means your design includes critical bugs.
     * Hence, in this design you are requested to design the data memory with the clock signal.
     * That means the written data is updated at the rising edge of the clock signal.
     */

    // Actually RISC-V supports misaligned data accesses to memory, however it this design the data memory will only support
    // the aligned memory accesses.

    logic   [31:0]  data[0:DMEM_DEPTH-1];

    // Write operation:
    always_ff @ (posedge clk) begin
        if (mem_write) begin
            data[addr] <= din;
        end
    end

    // Read operation:
    // - dout = 0 if (mem_read==0) 
    assign dout = mem_read ? data[addr] : 0;

/*
// synthesis translate_off
    initial begin
        $readmemh("dmem.mem", data);
    end
// synthesis translate_on
*/
endmodule

Lab3/dmem/wave.vcd
$version Generated by VerilatedVcd $end
$timescale 1ps $end
 $scope module TOP $end
  $var wire 1 # clk $end
  $var wire 10 $ addr [9:0] $end
  $var wire 32 % din [31:0] $end
  $var wire 1 & mem_read $end
  $var wire 1 ' mem_write $end
  $var wire 32 ( dout [31:0] $end
  $scope module dmem $end
   $var wire 32 ) DMEM_DEPTH [31:0] $end
   $var wire 32 * DMEM_ADDR_WIDTH [31:0] $end
   $var wire 1 # clk $end
   $var wire 10 $ addr [9:0] $end
   $var wire 32 % din [31:0] $end
   $var wire 1 & mem_read $end
   $var wire 1 ' mem_write $end
   $var wire 32 ( dout [31:0] $end
  $upscope $end
 $upscope $end
$enddefinitions $end


#0
1#
b0000000000 $
b00000000000000000000000000000000 %
0&
0'
b00000000000000000000000000000000 (
b00000000000000000000010000000000 )
b00000000000000000000000000001010 *
#5
0#
#10
1#
#15
0#
#20
1#
#25
0#
b0000000001 $
b00000000000000000000000000000010 %
1'
#30
1#
#35
0#
b0000000010 $
b00000000000000000000000000000100 %
#40
1#
#45
0#
b0000000011 $
b00000000000000000000000000000110 %
#50
1#
#55
0#
b0000000100 $
b00000000000000000000000000001000 %
#60
1#
#65
0#
b0000000101 $
b00000000000000000000000000001010 %
#70
1#
#75
0#
b0000000110 $
b00000000000000000000000000001100 %
#80
1#
#85
0#
b0000000111 $
b00000000000000000000000000001110 %
#90
1#
#95
0#
b0000001000 $
b00000000000000000000000000010000 %
#100
1#
#105
0#
b0000001001 $
b00000000000000000000000000010010 %
#110
1#
#115
0#
b0000001010 $
b00000000000000000000000000010100 %
#120
1#
#125
0#
b0000001011 $
b00000000000000000000000000010110 %
#130
1#
#135
0#
b0000001100 $
b00000000000000000000000000011000 %
#140
1#
#145
0#
b0000001101 $
b00000000000000000000000000011010 %
#150
1#
#155
0#
b0000001110 $
b00000000000000000000000000011100 %
#160
1#
#165
0#
b0000001111 $
b00000000000000000000000000011110 %
#170
1#
#175
0#
b0000000000 $
b00000000000000000000000000100000 %
#180
1#
#185
0#
b0000000001 $
b00000000000000000000000000100010 %
1&
0'
b00000000000000000000000000000010 (
#190
1#
#195
0#
b0000000010 $
b00000000000000000000000000100100 %
b00000000000000000000000000000100 (
#200
1#
#205
0#
b0000000011 $
b00000000000000000000000000100110 %
b00000000000000000000000000000110 (
#210
1#
#215
0#
b0000000100 $
b00000000000000000000000000101000 %
b00000000000000000000000000001000 (
#220
1#
#225
0#
b0000000101 $
b00000000000000000000000000101010 %
b00000000000000000000000000001010 (
#230
1#
#235
0#
b0000000110 $
b00000000000000000000000000101100 %
b00000000000000000000000000001100 (
#240
1#
#245
0#
b0000000111 $
b00000000000000000000000000101110 %
b00000000000000000000000000001110 (
#250
1#
#255
0#
b0000001000 $
b00000000000000000000000000110000 %
b00000000000000000000000000010000 (
#260
1#
#265
0#
b0000001001 $
b00000000000000000000000000110010 %
b00000000000000000000000000010010 (
#270
1#
#275
0#
b0000001010 $
b00000000000000000000000000110100 %
b00000000000000000000000000010100 (
#280
1#
#285
0#
b0000001011 $
b00000000000000000000000000110110 %
b00000000000000000000000000010110 (
#290
1#
#295
0#
b0000001100 $
b00000000000000000000000000111000 %
b00000000000000000000000000011000 (
#300
1#
#305
0#
b0000001101 $
b00000000000000000000000000111010 %
b00000000000000000000000000011010 (
#310
1#
#315
0#
b0000001110 $
b00000000000000000000000000111100 %
b00000000000000000000000000011100 (
#320
1#
#325
0#
b0000001111 $
b00000000000000000000000000111110 %
b00000000000000000000000000011110 (
#330
1#
#335
0#
b0000000000 $
b00000000000000000000000001000000 %
b00000000000000000000000000100000 (
#340
1#
#345
0#
b0000000001 $
b00000000000000000000000001000010 %
0&
b00000000000000000000000000000000 (
#350
1#
#355
0#
b0000000010 $
b00000000000000000000000001000100 %
