Lab1/sub2/sub2.sv
module sub2 (a, b, c);
    input [3:0] a, b;
    output [3:0] c;
    
    assign c = a - b;
endmodule

Lab1/sub2/wave.vcd
$version Generated by VerilatedVcd $end
$timescale 1ps $end
 $scope module TOP $end
  $var wire 4 # a [3:0] $end
  $var wire 4 $ b [3:0] $end
  $var wire 4 % c [3:0] $end
  $scope module sub2 $end
   $var wire 4 # a [3:0] $end
   $var wire 4 $ b [3:0] $end
   $var wire 4 % c [3:0] $end
  $upscope $end
 $upscope $end
$enddefinitions $end


#0
b0000 #
b1111 $
b0001 %
#1
b0001 #
b1110 $
b0011 %
#2
b0010 #
b1101 $
b0101 %
#3
b0011 #
b1100 $
b0111 %
#4
b0100 #
b1011 $
b1001 %
#5
b0101 #
b1010 $
b1011 %
#6
b0110 #
b1001 $
b1101 %
#7
b0111 #
b1000 $
b1111 %
#8
b1000 #
b0111 $
b0001 %
#9
b1001 #
b0110 $
b0011 %
#10
b1010 #
b0101 $
b0101 %
#11
b1011 #
b0100 $
b0111 %
#12
b1100 #
b0011 $
b1001 %
#13
b1101 #
b0010 $
b1011 %
#14
b1110 #
b0001 $
b1101 %
#15
b1111 #
b0000 $
b1111 %
