Lab3/alu/alu.sv
/* ********************************************
 *	COSE222 Lab #3
 *
 *	Module: ALU (alu.sv)
 *  - 32-bit 2 input and 1 output ports
 *
 *  Author: Gunjae Koo (gunjaekoo@korea.ac.kr)
 *
 * ********************************************
 */

`timescale 1ns/1ps

module alu
#(  parameter REG_WIDTH = 32 )  // ALU input data width is equal to the width of register file
(
    input   [REG_WIDTH-1:0] in1,    // Operand 1
    input   [REG_WIDTH-1:0] in2,    // Operand 2
    input   [3:0]   alu_control,    // ALU control signal
    output  logic [REG_WIDTH-1:0] result, // ALU output
    output          zero,           // Zero detection
    output          sign            // Sign bit
);

    always_comb begin
        case (alu_control)
            4'b0010: result = in1 + in2;    // lw, sw, add, addi
            4'b0110: result = in1 - in2;    // sub, beq, bne, blt, bge
            4'b0000: result = in1 & in2;    // and, andi
            4'b0001: result = in1 | in2;    // or, ori
            4'b0011: result = in1 ^ in2;    // xor, xori
            default: result = 0;            // default (to prevent latches)
		endcase
    end

    assign zero = (result == 0);
    assign sign = result[REG_WIDTH-1];

endmodule

Lab3/alu/wave.vcd
$version Generated by VerilatedVcd $end
$timescale 1ps $end
 $scope module TOP $end
  $var wire 32 # in1 [31:0] $end
  $var wire 32 $ in2 [31:0] $end
  $var wire 4 % alu_control [3:0] $end
  $var wire 32 & result [31:0] $end
  $var wire 1 ' zero $end
  $var wire 1 ( sign $end
  $scope module alu $end
   $var wire 32 ) REG_WIDTH [31:0] $end
   $var wire 32 # in1 [31:0] $end
   $var wire 32 $ in2 [31:0] $end
   $var wire 4 % alu_control [3:0] $end
   $var wire 32 & result [31:0] $end
   $var wire 1 ' zero $end
   $var wire 1 ( sign $end
  $upscope $end
 $upscope $end
$enddefinitions $end


#0
b00000000000000000000000000000111 #
b00000000000000000000000000000000 $
b0000 %
b00000000000000000000000000000000 &
1'
0(
b00000000000000000000000000100000 )
#5
#10
#15
#20
#25
b0001 %
b00000000000000000000000000000111 &
0'
#30
#35
b00000000000000000000000000000001 $
#40
#45
b00000000000000000000000000000010 $
#50
#55
b00000000000000000000000000000011 $
#60
#65
b00000000000000000000000000000100 $
#70
#75
b00000000000000000000000000000101 $
#80
#85
b00000000000000000000000000000110 $
#90
#95
b00000000000000000000000000000111 $
#100
#105
b00000000000000000000000000001000 $
b00000000000000000000000000001111 &
#110
#115
b00000000000000000000000000001001 $
#120
#125
b00000000000000000000000000001010 $
#130
#135
b00000000000000000000000000001011 $
#140
#145
b00000000000000000000000000001100 $
#150
#155
b00000000000000000000000000001101 $
#160
#165
b00000000000000000000000000001110 $
#170
#175
b00000000000000000000000000001111 $
#180
#185
b00000000000000000000000000000000 $
b0010 %
b00000000000000000000000000000111 &
#190
#195
b00000000000000000000000000000001 $
b00000000000000000000000000001000 &
#200
#205
b00000000000000000000000000000010 $
b00000000000000000000000000001001 &
#210
#215
b00000000000000000000000000000011 $
b00000000000000000000000000001010 &
#220
#225
b00000000000000000000000000000100 $
b00000000000000000000000000001011 &
#230
#235
b00000000000000000000000000000101 $
b00000000000000000000000000001100 &
#240
#245
b00000000000000000000000000000110 $
b00000000000000000000000000001101 &
#250
#255
b00000000000000000000000000000111 $
b00000000000000000000000000001110 &
#260
#265
b00000000000000000000000000001000 $
b00000000000000000000000000001111 &
#270
#275
b00000000000000000000000000001001 $
b00000000000000000000000000010000 &
#280
#285
b00000000000000000000000000001010 $
b00000000000000000000000000010001 &
#290
#295
b00000000000000000000000000001011 $
b00000000000000000000000000010010 &
#300
#305
b00000000000000000000000000001100 $
b00000000000000000000000000010011 &
#310
#315
b00000000000000000000000000001101 $
b00000000000000000000000000010100 &
#320
#325
b00000000000000000000000000001110 $
b00000000000000000000000000010101 &
#330
#335
b00000000000000000000000000001111 $
b00000000000000000000000000010110 &
#340
#345
b00000000000000000000000000000000 $
b0011 %
b00000000000000000000000000000111 &
#350
#355
b00000000000000000000000000000001 $
b00000000000000000000000000000110 &
#360
#365
b00000000000000000000000000000010 $
b00000000000000000000000000000101 &
#370
#375
b00000000000000000000000000000011 $
b00000000000000000000000000000100 &
#380
#385
b00000000000000000000000000000100 $
b00000000000000000000000000000011 &
#390
#395
b00000000000000000000000000000101 $
b00000000000000000000000000000010 &
#400
#405
b00000000000000000000000000000110 $
b00000000000000000000000000000001 &
#410
#415
b00000000000000000000000000000111 $
b00000000000000000000000000000000 &
1'
#420
#425
b00000000000000000000000000001000 $
b00000000000000000000000000001111 &
0'
#430
#435
b00000000000000000000000000001001 $
b00000000000000000000000000001110 &
#440
#445
b00000000000000000000000000001010 $
b00000000000000000000000000001101 &
#450
#455
b00000000000000000000000000001011 $
b00000000000000000000000000001100 &
#460
#465
b00000000000000000000000000001100 $
b00000000000000000000000000001011 &
#470
#475
b00000000000000000000000000001101 $
b00000000000000000000000000001010 &
#480
#485
b00000000000000000000000000001110 $
b00000000000000000000000000001001 &
#490
#495
b00000000000000000000000000001111 $
b00000000000000000000000000001000 &
#500
#505
b00000000000000000000000000000000 $
b0100 %
b00000000000000000000000000000000 &
1'
#510
#515
b00000000000000000000000000000001 $
#520
#525
b00000000000000000000000000000010 $
#530
#535
b00000000000000000000000000000011 $
#540
#545
b00000000000000000000000000000100 $
#550
#555
b00000000000000000000000000000101 $
#560
#565
b00000000000000000000000000000110 $
#570
#575
b00000000000000000000000000000111 $
#580
#585
b00000000000000000000000000001000 $
#590
#595
b00000000000000000000000000001001 $
#600
#605
b00000000000000000000000000001010 $
#610
#615
b00000000000000000000000000001011 $
#620
#625
b00000000000000000000000000001100 $
#630
#635
b00000000000000000000000000001101 $
#640
#645
b00000000000000000000000000001110 $
#650
#655
b00000000000000000000000000001111 $
#660
#665
b00000000000000000000000000000000 $
b0101 %
#670
#675
b00000000000000000000000000000001 $
#680
#685
b00000000000000000000000000000010 $
#690
#695
b00000000000000000000000000000011 $
#700
#705
b00000000000000000000000000000100 $
#710
#715
b00000000000000000000000000000101 $
#720
#725
b00000000000000000000000000000110 $
#730
#735
b00000000000000000000000000000111 $
#740
#745
b00000000000000000000000000001000 $
#750
#755
b00000000000000000000000000001001 $
#760
#765
b00000000000000000000000000001010 $
#770
#775
b00000000000000000000000000001011 $
#780
#785
b00000000000000000000000000001100 $
#790
#795
b00000000000000000000000000001101 $
#800
#805
b00000000000000000000000000001110 $
#810
#815
b00000000000000000000000000001111 $
#820
#825
b00000000000000000000000000000000 $
b0110 %
b00000000000000000000000000000111 &
0'
#830
#835
b00000000000000000000000000000001 $
b00000000000000000000000000000110 &
#840
#845
b00000000000000000000000000000010 $
b00000000000000000000000000000101 &
#850
#855
b00000000000000000000000000000011 $
b00000000000000000000000000000100 &
#860
#865
b00000000000000000000000000000100 $
b00000000000000000000000000000011 &
#870
#875
b00000000000000000000000000000101 $
b00000000000000000000000000000010 &
#880
#885
b00000000000000000000000000000110 $
b00000000000000000000000000000001 &
#890
#895
b00000000000000000000000000000111 $
b00000000000000000000000000000000 &
1'
#900
#905
b00000000000000000000000000001000 $
b11111111111111111111111111111111 &
0'
1(
#910
#915
b00000000000000000000000000001001 $
b11111111111111111111111111111110 &
#920
#925
b00000000000000000000000000001010 $
b11111111111111111111111111111101 &
#930
#935
b00000000000000000000000000001011 $
b11111111111111111111111111111100 &
#940
#945
b00000000000000000000000000001100 $
b11111111111111111111111111111011 &
#950
#955
b00000000000000000000000000001101 $
b11111111111111111111111111111010 &
#960
#965
b00000000000000000000000000001110 $
b11111111111111111111111111111001 &
#970
#975
b00000000000000000000000000001111 $
b11111111111111111111111111111000 &
#980
#985
b00000000000000000000000000000000 $
b0111 %
b00000000000000000000000000000000 &
1'
0(
#990
#995
b00000000000000000000000000000001 $
#1000
#1005
b00000000000000000000000000000010 $
#1010
#1015
b00000000000000000000000000000011 $
#1020
#1025
b00000000000000000000000000000100 $
#1030
#1035
b00000000000000000000000000000101 $
#1040
#1045
b00000000000000000000000000000110 $
#1050
#1055
b00000000000000000000000000000111 $
#1060
#1065
b00000000000000000000000000001000 $
#1070
#1075
b00000000000000000000000000001001 $
#1080
#1085
b00000000000000000000000000001010 $
#1090
#1095
b00000000000000000000000000001011 $
#1100
#1105
b00000000000000000000000000001100 $
#1110
#1115
b00000000000000000000000000001101 $
#1120
#1125
b00000000000000000000000000001110 $
#1130
#1135
b00000000000000000000000000001111 $
#1140
#1145
b00000000000000000000000000000000 $
b1000 %
