Lab3/regfile/regfile.sv
/* ********************************************
 *	COSE222 Lab #3
 *
 *	Module: register file (regfile.sv)
 *	- 2 input and 1 output ports
 *	- 32 register entries including zero register (x0)
 *  - No internal forwarding is supported
 *
 *	Author: Gunjae Koo (gunjaekoo@korea.ac.kr)
 *
 * ********************************************
 */

`timescale 1ns/1ps

module regfile
#(  parameter   REG_WIDTH = 32 )    // the width of register file
(
    input           clk,
    input   [4:0]   rs1,    // source register 1
    input   [4:0]   rs2,    // source register 2
    input   [4:0]   rd,     // destination register
    input   [REG_WIDTH-1:0] rd_din,     // input data for rd
    input           reg_write,      // RegWrite signal
    output  [REG_WIDTH-1:0] rs1_dout,
    output  [REG_WIDTH-1:0] rs2_dout
);

    // Registers: RISC-V includes 32 architectural registers
    logic   [REG_WIDTH-1:0] rf_data[0:31];

    // Write operation:
    // - Note that clock is not used in the textbook, however in RTL design it can generate a infinite loop without clock.
    // Thus, the write operation is done at the rising edge of clock
    always_ff @ (posedge clk) begin
        if (reg_write) begin
            rf_data[rd] <= rd_din;
        end
    end

    // Read operation
    assign rs1_dout = (rs1 == 0) ? 0 : rf_data[rs1];
    assign rs2_dout = (rs2 == 0) ? 0 : rf_data[rs2];

endmodule

Lab3/regfile/wave.vcd
$version Generated by VerilatedVcd $end
$timescale 1ps $end
 $scope module TOP $end
  $var wire 1 C clk $end
  $var wire 5 D rs1 [4:0] $end
  $var wire 5 E rs2 [4:0] $end
  $var wire 5 F rd [4:0] $end
  $var wire 32 G rd_din [31:0] $end
  $var wire 1 H reg_write $end
  $var wire 32 I rs1_dout [31:0] $end
  $var wire 32 J rs2_dout [31:0] $end
  $scope module regfile $end
   $var wire 32 K REG_WIDTH [31:0] $end
   $var wire 1 C clk $end
   $var wire 5 D rs1 [4:0] $end
   $var wire 5 E rs2 [4:0] $end
   $var wire 5 F rd [4:0] $end
   $var wire 32 G rd_din [31:0] $end
   $var wire 1 H reg_write $end
   $var wire 32 I rs1_dout [31:0] $end
   $var wire 32 J rs2_dout [31:0] $end
   $var wire 32 # rf_data[0] [31:0] $end
   $var wire 32 $ rf_data[1] [31:0] $end
   $var wire 32 % rf_data[2] [31:0] $end
   $var wire 32 & rf_data[3] [31:0] $end
   $var wire 32 ' rf_data[4] [31:0] $end
   $var wire 32 ( rf_data[5] [31:0] $end
   $var wire 32 ) rf_data[6] [31:0] $end
   $var wire 32 * rf_data[7] [31:0] $end
   $var wire 32 + rf_data[8] [31:0] $end
   $var wire 32 , rf_data[9] [31:0] $end
   $var wire 32 - rf_data[10] [31:0] $end
   $var wire 32 . rf_data[11] [31:0] $end
   $var wire 32 / rf_data[12] [31:0] $end
   $var wire 32 0 rf_data[13] [31:0] $end
   $var wire 32 1 rf_data[14] [31:0] $end
   $var wire 32 2 rf_data[15] [31:0] $end
   $var wire 32 3 rf_data[16] [31:0] $end
   $var wire 32 4 rf_data[17] [31:0] $end
   $var wire 32 5 rf_data[18] [31:0] $end
   $var wire 32 6 rf_data[19] [31:0] $end
   $var wire 32 7 rf_data[20] [31:0] $end
   $var wire 32 8 rf_data[21] [31:0] $end
   $var wire 32 9 rf_data[22] [31:0] $end
   $var wire 32 : rf_data[23] [31:0] $end
   $var wire 32 ; rf_data[24] [31:0] $end
   $var wire 32 < rf_data[25] [31:0] $end
   $var wire 32 = rf_data[26] [31:0] $end
   $var wire 32 > rf_data[27] [31:0] $end
   $var wire 32 ? rf_data[28] [31:0] $end
   $var wire 32 @ rf_data[29] [31:0] $end
   $var wire 32 A rf_data[30] [31:0] $end
   $var wire 32 B rf_data[31] [31:0] $end
  $upscope $end
 $upscope $end
$enddefinitions $end


#0
b00000000000000000000000000000000 #
b00000000000000000000000000000000 $
b00000000000000000000000000000000 %
b00000000000000000000000000000000 &
b00000000000000000000000000000000 '
b00000000000000000000000000000000 (
b00000000000000000000000000000000 )
b00000000000000000000000000000000 *
b00000000000000000000000000000000 +
b00000000000000000000000000000000 ,
b00000000000000000000000000000000 -
b00000000000000000000000000000000 .
b00000000000000000000000000000000 /
b00000000000000000000000000000000 0
b00000000000000000000000000000000 1
b00000000000000000000000000000000 2
b00000000000000000000000000000000 3
b00000000000000000000000000000000 4
b00000000000000000000000000000000 5
b00000000000000000000000000000000 6
b00000000000000000000000000000000 7
b00000000000000000000000000000000 8
b00000000000000000000000000000000 9
b00000000000000000000000000000000 :
b00000000000000000000000000000000 ;
b00000000000000000000000000000000 <
b00000000000000000000000000000000 =
b00000000000000000000000000000000 >
b00000000000000000000000000000000 ?
b00000000000000000000000000000000 @
b00000000000000000000000000000000 A
b00000000000000000000000000000000 B
1C
b00000 D
b00000 E
b00000 F
b00000000000000000000000000000000 G
0H
b00000000000000000000000000000000 I
b00000000000000000000000000000000 J
b00000000000000000000000000100000 K
#5
0C
#10
1C
#15
0C
#20
1C
#25
0C
b00001 D
b00010 E
b00001 F
b00000000000000000000000000000100 G
1H
#30
b00000000000000000000000000000100 $
1C
b00000000000000000000000000000100 I
#35
0C
b00010 D
b00011 E
b00010 F
b00000000000000000000000000001000 G
b00000000000000000000000000000000 I
#40
b00000000000000000000000000001000 %
1C
b00000000000000000000000000001000 I
#45
0C
b00011 D
b00100 E
b00011 F
b00000000000000000000000000001100 G
b00000000000000000000000000000000 I
#50
b00000000000000000000000000001100 &
1C
b00000000000000000000000000001100 I
#55
0C
b00100 D
b00101 E
b00100 F
b00000000000000000000000000010000 G
b00000000000000000000000000000000 I
#60
b00000000000000000000000000010000 '
1C
b00000000000000000000000000010000 I
#65
0C
b00101 D
b00110 E
b00101 F
b00000000000000000000000000010100 G
b00000000000000000000000000000000 I
#70
b00000000000000000000000000010100 (
1C
b00000000000000000000000000010100 I
#75
0C
b00110 D
b00111 E
b00110 F
b00000000000000000000000000011000 G
b00000000000000000000000000000000 I
#80
b00000000000000000000000000011000 )
1C
b00000000000000000000000000011000 I
#85
0C
b00111 D
b01000 E
b00111 F
b00000000000000000000000000011100 G
b00000000000000000000000000000000 I
#90
b00000000000000000000000000011100 *
1C
b00000000000000000000000000011100 I
#95
0C
b01000 D
b01001 E
b01000 F
b00000000000000000000000000100000 G
b00000000000000000000000000000000 I
#100
b00000000000000000000000000100000 +
1C
b00000000000000000000000000100000 I
#105
0C
b01001 D
b01010 E
b01001 F
b00000000000000000000000000100100 G
b00000000000000000000000000000000 I
#110
b00000000000000000000000000100100 ,
1C
b00000000000000000000000000100100 I
#115
0C
b01010 D
b01011 E
b01010 F
b00000000000000000000000000101000 G
b00000000000000000000000000000000 I
#120
b00000000000000000000000000101000 -
1C
b00000000000000000000000000101000 I
#125
0C
b01011 D
b01100 E
b01011 F
b00000000000000000000000000101100 G
b00000000000000000000000000000000 I
#130
b00000000000000000000000000101100 .
1C
b00000000000000000000000000101100 I
#135
0C
b01100 D
b01101 E
b01100 F
b00000000000000000000000000110000 G
b00000000000000000000000000000000 I
#140
b00000000000000000000000000110000 /
1C
b00000000000000000000000000110000 I
#145
0C
b01101 D
b01110 E
b01101 F
b00000000000000000000000000110100 G
b00000000000000000000000000000000 I
#150
b00000000000000000000000000110100 0
1C
b00000000000000000000000000110100 I
#155
0C
b01110 D
b01111 E
b01110 F
b00000000000000000000000000111000 G
b00000000000000000000000000000000 I
#160
b00000000000000000000000000111000 1
1C
b00000000000000000000000000111000 I
#165
0C
b01111 D
b10000 E
b01111 F
b00000000000000000000000000111100 G
b00000000000000000000000000000000 I
#170
b00000000000000000000000000111100 2
1C
b00000000000000000000000000111100 I
#175
0C
b10000 D
b10001 E
b10000 F
b00000000000000000000000001000000 G
b00000000000000000000000000000000 I
#180
b00000000000000000000000001000000 3
1C
b00000000000000000000000001000000 I
#185
0C
b10001 D
b10010 E
b10001 F
b00000000000000000000000001000100 G
b00000000000000000000000000000000 I
#190
b00000000000000000000000001000100 4
1C
b00000000000000000000000001000100 I
#195
0C
b10010 D
b10011 E
b10010 F
b00000000000000000000000001001000 G
b00000000000000000000000000000000 I
#200
b00000000000000000000000001001000 5
1C
b00000000000000000000000001001000 I
#205
0C
b10011 D
b10100 E
b10011 F
b00000000000000000000000001001100 G
b00000000000000000000000000000000 I
#210
b00000000000000000000000001001100 6
1C
b00000000000000000000000001001100 I
#215
0C
b10100 D
b10101 E
b10100 F
b00000000000000000000000001010000 G
b00000000000000000000000000000000 I
#220
b00000000000000000000000001010000 7
1C
b00000000000000000000000001010000 I
#225
0C
b10101 D
b10110 E
b10101 F
b00000000000000000000000001010100 G
b00000000000000000000000000000000 I
#230
b00000000000000000000000001010100 8
1C
b00000000000000000000000001010100 I
#235
0C
b10110 D
b10111 E
b10110 F
b00000000000000000000000001011000 G
b00000000000000000000000000000000 I
#240
b00000000000000000000000001011000 9
1C
b00000000000000000000000001011000 I
#245
0C
b10111 D
b11000 E
b10111 F
b00000000000000000000000001011100 G
b00000000000000000000000000000000 I
#250
b00000000000000000000000001011100 :
1C
b00000000000000000000000001011100 I
#255
0C
b11000 D
b11001 E
b11000 F
b00000000000000000000000001100000 G
b00000000000000000000000000000000 I
#260
b00000000000000000000000001100000 ;
1C
b00000000000000000000000001100000 I
#265
0C
b11001 D
b11010 E
b11001 F
b00000000000000000000000001100100 G
b00000000000000000000000000000000 I
#270
b00000000000000000000000001100100 <
1C
b00000000000000000000000001100100 I
#275
0C
b11010 D
b11011 E
b11010 F
b00000000000000000000000001101000 G
b00000000000000000000000000000000 I
#280
b00000000000000000000000001101000 =
1C
b00000000000000000000000001101000 I
#285
0C
b11011 D
b11100 E
b11011 F
b00000000000000000000000001101100 G
b00000000000000000000000000000000 I
#290
b00000000000000000000000001101100 >
1C
b00000000000000000000000001101100 I
#295
0C
b11100 D
b11101 E
b11100 F
b00000000000000000000000001110000 G
b00000000000000000000000000000000 I
#300
b00000000000000000000000001110000 ?
1C
b00000000000000000000000001110000 I
#305
0C
b11101 D
b11110 E
b11101 F
b00000000000000000000000001110100 G
b00000000000000000000000000000000 I
#310
b00000000000000000000000001110100 @
1C
b00000000000000000000000001110100 I
#315
0C
b11110 D
b11111 E
b11110 F
b00000000000000000000000001111000 G
b00000000000000000000000000000000 I
#320
b00000000000000000000000001111000 A
1C
b00000000000000000000000001111000 I
#325
0C
b11111 D
b00000 E
b11111 F
b00000000000000000000000001111100 G
b00000000000000000000000000000000 I
#330
b00000000000000000000000001111100 B
1C
b00000000000000000000000001111100 I
#335
0C
b00000 D
b00001 E
b00000 F
b00000000000000000000000010000000 G
b00000000000000000000000000000000 I
b00000000000000000000000000000100 J
#340
b00000000000000000000000010000000 #
1C
#345
0C
b00001 D
b00010 E
b00001 F
b00000000000000000000000010000100 G
0H
b00000000000000000000000000000100 I
b00000000000000000000000000001000 J
#350
1C
#355
0C
b00010 D
b00011 E
b00010 F
b00000000000000000000000010001000 G
b00000000000000000000000000001000 I
b00000000000000000000000000001100 J
#360
1C
#365
0C
b00011 D
b00100 E
b00011 F
b00000000000000000000000010001100 G
b00000000000000000000000000001100 I
b00000000000000000000000000010000 J
#370
1C
#375
0C
b00100 D
b00101 E
b00100 F
b00000000000000000000000010010000 G
b00000000000000000000000000010000 I
b00000000000000000000000000010100 J
#380
1C
#385
0C
b00101 D
b00110 E
b00101 F
b00000000000000000000000010010100 G
b00000000000000000000000000010100 I
b00000000000000000000000000011000 J
#390
1C
#395
0C
b00110 D
b00111 E
b00110 F
b00000000000000000000000010011000 G
b00000000000000000000000000011000 I
b00000000000000000000000000011100 J
#400
1C
#405
0C
b00111 D
b01000 E
b00111 F
b00000000000000000000000010011100 G
b00000000000000000000000000011100 I
b00000000000000000000000000100000 J
#410
1C
#415
0C
b01000 D
b01001 E
b01000 F
b00000000000000000000000010100000 G
b00000000000000000000000000100000 I
b00000000000000000000000000100100 J
#420
1C
#425
0C
b01001 D
b01010 E
b01001 F
b00000000000000000000000010100100 G
b00000000000000000000000000100100 I
b00000000000000000000000000101000 J
#430
1C
#435
0C
b01010 D
b01011 E
b01010 F
b00000000000000000000000010101000 G
b00000000000000000000000000101000 I
b00000000000000000000000000101100 J
#440
1C
#445
0C
b01011 D
b01100 E
b01011 F
b00000000000000000000000010101100 G
b00000000000000000000000000101100 I
b00000000000000000000000000110000 J
#450
1C
#455
0C
b01100 D
b01101 E
b01100 F
b00000000000000000000000010110000 G
b00000000000000000000000000110000 I
b00000000000000000000000000110100 J
#460
1C
#465
0C
b01101 D
b01110 E
b01101 F
b00000000000000000000000010110100 G
b00000000000000000000000000110100 I
b00000000000000000000000000111000 J
#470
1C
#475
0C
b01110 D
b01111 E
b01110 F
b00000000000000000000000010111000 G
b00000000000000000000000000111000 I
b00000000000000000000000000111100 J
#480
1C
#485
0C
b01111 D
b10000 E
b01111 F
b00000000000000000000000010111100 G
b00000000000000000000000000111100 I
b00000000000000000000000001000000 J
#490
1C
#495
0C
b10000 D
b10001 E
b10000 F
b00000000000000000000000011000000 G
b00000000000000000000000001000000 I
b00000000000000000000000001000100 J
#500
1C
#505
0C
b10001 D
b10010 E
b10001 F
b00000000000000000000000011000100 G
b00000000000000000000000001000100 I
b00000000000000000000000001001000 J
#510
1C
#515
0C
b10010 D
b10011 E
b10010 F
b00000000000000000000000011001000 G
b00000000000000000000000001001000 I
b00000000000000000000000001001100 J
#520
1C
#525
0C
b10011 D
b10100 E
b10011 F
b00000000000000000000000011001100 G
b00000000000000000000000001001100 I
b00000000000000000000000001010000 J
#530
1C
#535
0C
b10100 D
b10101 E
b10100 F
b00000000000000000000000011010000 G
b00000000000000000000000001010000 I
b00000000000000000000000001010100 J
#540
1C
#545
0C
b10101 D
b10110 E
b10101 F
b00000000000000000000000011010100 G
b00000000000000000000000001010100 I
b00000000000000000000000001011000 J
#550
1C
#555
0C
b10110 D
b10111 E
b10110 F
b00000000000000000000000011011000 G
b00000000000000000000000001011000 I
b00000000000000000000000001011100 J
#560
1C
#565
0C
b10111 D
b11000 E
b10111 F
b00000000000000000000000011011100 G
b00000000000000000000000001011100 I
b00000000000000000000000001100000 J
#570
1C
#575
0C
b11000 D
b11001 E
b11000 F
b00000000000000000000000011100000 G
b00000000000000000000000001100000 I
b00000000000000000000000001100100 J
#580
1C
#585
0C
b11001 D
b11010 E
b11001 F
b00000000000000000000000011100100 G
b00000000000000000000000001100100 I
b00000000000000000000000001101000 J
#590
1C
#595
0C
b11010 D
b11011 E
b11010 F
b00000000000000000000000011101000 G
b00000000000000000000000001101000 I
b00000000000000000000000001101100 J
#600
1C
#605
0C
b11011 D
b11100 E
b11011 F
b00000000000000000000000011101100 G
b00000000000000000000000001101100 I
b00000000000000000000000001110000 J
#610
1C
#615
0C
b11100 D
b11101 E
b11100 F
b00000000000000000000000011110000 G
b00000000000000000000000001110000 I
b00000000000000000000000001110100 J
#620
1C
#625
0C
b11101 D
b11110 E
b11101 F
b00000000000000000000000011110100 G
b00000000000000000000000001110100 I
b00000000000000000000000001111000 J
#630
1C
#635
0C
b11110 D
b11111 E
b11110 F
b00000000000000000000000011111000 G
b00000000000000000000000001111000 I
b00000000000000000000000001111100 J
#640
1C
#645
0C
b11111 D
b00000 E
b11111 F
b00000000000000000000000011111100 G
b00000000000000000000000001111100 I
b00000000000000000000000000000000 J
#650
1C
#655
0C
b00000 D
b00001 E
b00000 F
b00000000000000000000000100000000 G
b00000000000000000000000000000000 I
b00000000000000000000000000000100 J
#660
1C
#665
0C
b00001 D
b00010 E
b00001 F
b00000000000000000000000100000100 G
b00000000000000000000000000000100 I
b00000000000000000000000000001000 J
#670
1C
#675
0C
b00010 D
b00011 E
b00010 F
b00000000000000000000000100001000 G
b00000000000000000000000000001000 I
b00000000000000000000000000001100 J
