Lab4/dmem.sv
/* ********************************************
 *	COSE222 Lab #4
 *
 *	Module: data memory (dmem.sv)
 *	- 1 address input port
 *	- 32-bit 1 data input and output ports
 *	- A single entry size is 64-bit
 *
 *	Author: Gunjae Koo (gunjaekoo@korea.ac.kr)
 *
 * ********************************************
 */

`timescale 1ns/1ps

module dmem
#(  parameter DMEM_DEPTH = 1024,    // dmem depth (default: 1024 entries = 8 KB)
              DMEM_ADDR_WIDTH = 10 )
(
    input           clk,
    input   [DMEM_ADDR_WIDTH-1:0]   addr,
    input   [31:0]  din,
    input           mem_read,
    input           mem_write,
    output  [31:0]  dout
);

    /* Data memory does not receive the clock signal in the textbook.
     * Without clock we need to implement the data memory with latches.
     * However, you must avoid generating latches in real RTL design.
     * If latches are generated after synthesis, then it means your design includes critical bugs.
     * Hence, in this design you are requested to design the data memory with the clock signal.
     * That means the written data is updated at the rising edge of the clock signal.
     */

    // Actually RISC-V supports misaligned data accesses to memory, however it this design the data memory will only support
    // the aligned memory accesses.

    logic   [31:0]  data[0:DMEM_DEPTH-1];

    // Write operation:
    always_ff @ (posedge clk) begin
        if (mem_write)
            data[addr] <= din;
    end

    // Read operation:
    // - dout = 0 if (mem_read==0) 
    assign dout = (mem_read) ? data[addr]: 'b0;

// synthesis translate_off
    initial begin
        $readmemh("dmem.mem", data);
    end
// synthesis translate_on

endmodule

Lab4/alu.sv
/* ********************************************
 *	COSE222 Lab #4
 *
 *	Module: ALU (alu.sv)
 *  - 64-bit 2 input and 1 output ports
 *
 *  Author: Gunjae Koo (gunjaekoo@korea.ac.kr)
 *
 * ********************************************
 */

`timescale 1ns/1ps

module alu
#(  parameter REG_WIDTH = 32 )  // ALU input data width is equal to the width of register file
(
    input   [REG_WIDTH-1:0] in1,    // Operand 1
    input   [REG_WIDTH-1:0] in2,    // Operand 2
    input   [3:0]   alu_control,    // ALU control signal
    output  logic [REG_WIDTH-1:0] result, // ALU output
    output          zero,           // Zero detection
    output          sign            // Sign bit
);

    always_comb begin
        case (alu_control)
            4'b0000: result = in1 & in2;
            4'b0001: result = in1 | in2;
            //4'b0010: result = in1 + in2;
			4'b0011: result = in1 ^ in2;
            4'b0110: result = in1 - in2;
            default: result = in1 + in2;    // default = add
		endcase
    end

    assign zero = ~|result;
    assign sign = result[REG_WIDTH-1];

endmodule

Lab4/regfile.sv
/* ********************************************
 *	COSE222 Lab #4
 *
 *	Module: register file (regfile.sv)
 *	- 2 input and 1 output ports
 *	- 32 register entries including zero register (x0)
 *  - No internal forwarding is supported
 *
 *	Author: Gunjae Koo (gunjaekoo@korea.ac.kr)
 *
 * ********************************************
 */

`timescale 1ns/1ps

module regfile
#(  parameter   REG_WIDTH = 32 )    // the width of register file
(
    input           clk,
    input   [4:0]   rs1,    // source register 1
    input   [4:0]   rs2,    // source register 2
    input   [4:0]   rd,     // destination register
    input   [REG_WIDTH-1:0] rd_din,     // input data for rd
    input           reg_write,      // RegWrite signal
    output  [REG_WIDTH-1:0] rs1_dout,
    output  [REG_WIDTH-1:0] rs2_dout
);

    // Registers: RISC-V includes 32 architectural registers
    logic   [REG_WIDTH-1:0] rf_data[0:31];

    // Write operation:
    // - Note that clock is not used in the textbook, however in RTL design it can generate a infinite loop without clock.
    // Thus, the write operation is done at the rising edge of clock
    always_ff @ (posedge clk) begin
        if (reg_write)
            rf_data[rd] <= rd_din;
    end

    // Read operation
    assign rs1_dout = (|rs1) ? rf_data[rs1]: 'b0;
    assign rs2_dout = (|rs2) ? rf_data[rs2]: 'b0;

endmodule

Lab4/imem.sv
/* ********************************************
 *	COSE222 Lab #4
 *
 *	Module: instruction memory (imem.sv)
 *	- 1 address input port
 *	- 32-bit 1 data output port
 *	- A single entry size is 32 bit, which is equivalent to the RISC-V instruction size
 *
 *	Author: Gunjae Koo (gunjaekoo@korea.ac.kr)
 *
 * ********************************************
 */

`timescale 1ns/1ps

module imem
#(  parameter IMEM_DEPTH = 1024,    // imem depth (default: 1024 entries = 4 KB)
              IMEM_ADDR_WIDTH = 10 )
(
    input   [IMEM_ADDR_WIDTH-1:0]   addr,
    output  [31:0]  dout
);

    logic   [31:0]  data[0:IMEM_DEPTH-1];

    assign dout = data[addr];

// synthesis translate_off
    initial begin
        for (int i = 0; i < IMEM_DEPTH; i++)
            data[i] = 'b0;
        $readmemb("imem.mem", data);
    end
// synthesis translate_on

endmodule

Lab4/single_cycle_cpu.sv
/* ********************************************
 *	COSE222 Lab #4
 *
 *	Module: top design of the single-cycle CPU (single_cycle_cpu.sv)
 *  - Top design of the single-cycle CPU
 *
 *  Author: Gunjae Koo (gunjaekoo@korea.ac.kr)
 *
 * ********************************************
 */

`timescale 1ns/1ps

module single_cycle_cpu
#(  parameter IMEM_DEPTH = 1024,    // imem depth (default: 1024 entries = 4 KB)
              IMEM_ADDR_WIDTH = 10,
              REG_WIDTH = 32,
              DMEM_DEPTH = 1024,    // dmem depth (default: 1024 entries = 8 KB)
              DMEM_ADDR_WIDTH = 10 )
(
    input           clk,            // System clock
    input           reset_b         // Asychronous negative reset
);

    // Wires for datapath elements
    logic   [IMEM_ADDR_WIDTH-1:0]   imem_addr;
    logic   [31:0]  inst;   // instructions = an output of imem

    logic   [4:0]   rs1, rs2, rd;    // register numbers
    logic   [REG_WIDTH-1:0] rd_din;
    logic           reg_write;
    logic   [REG_WIDTH-1:0] rs1_dout, rs2_dout;

    logic   [REG_WIDTH-1:0] alu_in1, alu_in2;
    logic   [3:0]   alu_control;    // ALU control signal
    logic   [REG_WIDTH-1:0] alu_result;
    logic           alu_zero;
    logic           alu_sign;

    logic   [DMEM_ADDR_WIDTH-1:0]    dmem_addr;
    logic   [31:0]  dmem_din, dmem_dout;
    logic           mem_read, mem_write;

    // -------------------------------------------------------------------
    /* Main control unit:
     * Main control unit generates control signals for datapath elements
     * The control signals are determined by decoding instructions
     * Generating control signals using opcode = inst[6:0]
     */
    logic   [6:0]   opcode;
    logic   [3:0]   branch;
    logic           alu_src, mem_to_reg;
    logic   [1:0]   alu_op;
    logic   [2:0]   funct3;
    //logic         mem_read, mem_write, reg_write; // declared above
    // Note for Lab #5
    // The branch control signal has 4-bits since this processor supports beq, bne, blt, and bge
    // Each bit of the branch control signal represents the corresponding branch instruction
    // i.e., branch[0] = beq, branch[1] = bne, branch[2] = blt, branch[3] = bge

    // COMPLETE THE MAIN CONTROL UNIT HERE
    assign opcode = inst[6:0];
    assign funct3 = inst[14:12];

    assign branch[0] = (opcode == 7'b1100011 && funct3 == 3'b000);  // beq
    assign branch[1] = (opcode == 7'b1100011 && funct3 == 3'b001);  // bne
    assign branch[2] = (opcode == 7'b1100011 && funct3 == 3'b100);  // blt
    assign branch[3] = (opcode == 7'b1100011 && funct3 == 3'b101);  // bge

    assign mem_read = (opcode == 7'b0000011);   // ld
    assign mem_write = (opcode == 7'b0100011);  // sd
    assign mem_to_reg = (opcode == 7'b0000011); // ld
    assign reg_write = (opcode == 7'b0000011 || opcode == 7'b0110011 || opcode == 7'b0010011);  // ld, r-type, or i-type
    assign alu_src = (opcode == 7'b0000011 || opcode == 7'b0100011 || opcode == 7'b0010011);    // ld, sd, or i-type

    assign alu_op[0] = (opcode == 7'b1100011);  // branch
    assign alu_op[1] = (opcode == 7'b0110011 || opcode == 7'b0010011);  // r-type or i-type


    // --------------------------------------------------------------------

    // --------------------------------------------------------------------
    /* ALU control unit:
     * ALU control unit generate alu_control signal which selects ALU operations
     * Generating control signals using alu_op, funct7, and funct3 fileds
     */
    logic   [6:0]   funct7;
    //logic   [2:0]   funct3;   // declared above

    // COMPLETE THE ALU CONTROL UNIT HERE
    assign funct7 = inst[31:25];

    always_comb begin
        case (alu_op)
            2'b00: alu_control = 4'b0010;   // load, store -> add
            2'b01: alu_control = 4'b0110;   // branch -> sub
            2'b10:
                case (funct3)
                    3'b000: alu_control = (funct7 == 7'b0100000) ? 4'b0110 : 4'b0010;   // sub, add
                    3'b100: alu_control = 4'b0011;  // xor
                    3'b110: alu_control = 4'b0001;  // or
                    3'b111: alu_control = 4'b0000;  // and
                    default: alu_control = 4'b0010; // default -> add
                endcase
            default: alu_control = 4'b0010; // default -> add
        endcase
    end



    // ---------------------------------------------------------------------


    // ---------------------------------------------------------------------
    /* Immediate generator:
     * Generating immediate value from inst[31:0]
     * We require immediate type data for load, store, i-type, and branch instructions
     */
    logic   [REG_WIDTH-1:0]  imm32;
    logic   [REG_WIDTH-1:0]  imm32_branch;  // imm32 left shifted by 1
    logic   [11:0]  imm12;  // 12-bit immediate value extracted from inst

    // COMPLETE IMMEDIATE GENERATOR HERE
    always_comb begin
        case (opcode)
	        7'b0000011: imm12 = inst[31:20];    // I-type
	        7'b0010011: imm12 = inst[31:20];    // I-type
	        7'b0100011: imm12 = {inst[31:25], inst[11:7]};  // S-type
	        7'b1100011: imm12 = {inst[31], inst[7], inst[30:25], inst[11:8]};  // SB-type
	        default: imm12 = 12'b0; // default: 0
        endcase
    end
	
    assign imm32 = {{20{imm12[11]}}, imm12[11:0]};
    assign imm32_branch = imm32 << 1;



    // ----------------------------------------------------------------------

    // Program counter
    logic   [31:0]  pc_curr, pc_next;
    logic           pc_next_sel;    // selection signal for pc_next
    logic   [31:0]  pc_next_plus4, pc_next_branch;


    assign pc_next_plus4 = pc_curr + 4; // FILL THIS

    always_ff @ (posedge clk or negedge reset_b) begin
        if (~reset_b) begin
            pc_curr <= 'b0;
        end else begin
            pc_curr <= pc_next; // FILL THIS
        end
    end


    // MUXes:
    // COMPLETE MUXES HERE
    // PC_NEXT
    assign pc_next_sel = ((branch[0] && alu_zero)       // beq 
                        || (branch[1] && ~alu_zero)     // bne 
                        || (branch[2] && alu_sign)      // blt 
                        || (branch[3] && ~alu_sign));   // bge  // FILL THIS 
    assign pc_next = pc_next_sel ? pc_next_branch : pc_next_plus4;  // if branch is taken, pc_next_sel=1'b1
    assign pc_next_branch = pc_curr + imm32_branch;                 // FILL THIS

    // ALU inputs
    assign alu_in1 = rs1_dout;
    assign alu_in2 = alu_src ? imm32 : rs2_dout;

    // RF din
    assign rd_din = mem_to_reg ? dmem_dout : alu_result;

    // COMPLETE CONNECTIONS HERE
    // imem
    assign imem_addr = pc_curr[IMEM_ADDR_WIDTH+1:2];

    // regfile
    assign rs1 = inst[19:15];
    assign rs2 = inst[24:20];
    assign rd = inst[11:7];

    // dmem
    assign dmem_addr = alu_result[DMEM_ADDR_WIDTH+1:2];
    assign dmem_din = rs2_dout;
 

    // -----------------------------------------------------------------------
    /* Instantiation of datapath elements
     * All input/output ports should be connected
     */
    
    // IMEM
    imem #(
        .IMEM_DEPTH         (IMEM_DEPTH),
        .IMEM_ADDR_WIDTH    (IMEM_ADDR_WIDTH)
    ) u_imem_0 (
        .addr               ( imem_addr     ),
        .dout               ( inst          )
    );

    // REGFILE
	regfile #(
		.REG_WIDTH (REG_WIDTH)
	) u_regfile_0(
		.clk (clk),
		.rs1 (rs1),
		.rs2 (rs2),
		.rd (rd),
		.rd_din (rd_din),
		.reg_write (reg_write),
		.rs1_dout (rs1_dout),
		.rs2_dout (rs2_dout)
	);

    // ALU
	alu #(
		.REG_WIDTH (REG_WIDTH)
	) u_alu_0 (
		.in1 (alu_in1),
		.in2 (alu_in2),
		.alu_control (alu_control),
		.result (alu_result),
		.zero (alu_zero),
		.sign (alu_sign)
	);

    // DMEM
	dmem #(
		.DMEM_DEPTH (DMEM_DEPTH),
		.DMEM_ADDR_WIDTH (DMEM_ADDR_WIDTH)
	) u_dmem_0(
		.clk (clk),
		.addr (dmem_addr),
		.din (dmem_din),
		.mem_read (mem_read),
		.mem_write (mem_write),
		.dout (dmem_dout)
	);
endmodule

Lab4/wave.vcd
$version Generated by VerilatedVcd $end
$timescale 1ps $end
 $scope module TOP $end
  $var wire 1 _ clk $end
  $var wire 1 ` reset_b $end
  $scope module single_cycle_cpu $end
   $var wire 32 f IMEM_DEPTH [31:0] $end
   $var wire 32 g IMEM_ADDR_WIDTH [31:0] $end
   $var wire 32 h REG_WIDTH [31:0] $end
   $var wire 32 f DMEM_DEPTH [31:0] $end
   $var wire 32 g DMEM_ADDR_WIDTH [31:0] $end
   $var wire 1 _ clk $end
   $var wire 1 ` reset_b $end
   $var wire 10 D imem_addr [9:0] $end
   $var wire 32 E inst [31:0] $end
   $var wire 5 F rs1 [4:0] $end
   $var wire 5 G rs2 [4:0] $end
   $var wire 5 H rd [4:0] $end
   $var wire 32 a rd_din [31:0] $end
   $var wire 1 I reg_write $end
   $var wire 32 b rs1_dout [31:0] $end
   $var wire 32 Y rs2_dout [31:0] $end
   $var wire 32 b alu_in1 [31:0] $end
   $var wire 32 Z alu_in2 [31:0] $end
   $var wire 4 J alu_control [3:0] $end
   $var wire 32 [ alu_result [31:0] $end
   $var wire 1 \ alu_zero $end
   $var wire 1 ] alu_sign $end
   $var wire 10 ^ dmem_addr [9:0] $end
   $var wire 32 Y dmem_din [31:0] $end
   $var wire 32 c dmem_dout [31:0] $end
   $var wire 1 K mem_read $end
   $var wire 1 L mem_write $end
   $var wire 7 M opcode [6:0] $end
   $var wire 4 N branch [3:0] $end
   $var wire 1 O alu_src $end
   $var wire 1 K mem_to_reg $end
   $var wire 2 P alu_op [1:0] $end
   $var wire 3 Q funct3 [2:0] $end
   $var wire 7 R funct7 [6:0] $end
   $var wire 32 S imm32 [31:0] $end
   $var wire 32 T imm32_branch [31:0] $end
   $var wire 12 U imm12 [11:0] $end
   $var wire 32 V pc_curr [31:0] $end
   $var wire 32 d pc_next [31:0] $end
   $var wire 1 e pc_next_sel $end
   $var wire 32 W pc_next_plus4 [31:0] $end
   $var wire 32 X pc_next_branch [31:0] $end
   $scope module u_alu_0 $end
    $var wire 32 h REG_WIDTH [31:0] $end
    $var wire 32 b in1 [31:0] $end
    $var wire 32 Z in2 [31:0] $end
    $var wire 4 J alu_control [3:0] $end
    $var wire 32 [ result [31:0] $end
    $var wire 1 \ zero $end
    $var wire 1 ] sign $end
   $upscope $end
   $scope module u_dmem_0 $end
    $var wire 32 f DMEM_DEPTH [31:0] $end
    $var wire 32 g DMEM_ADDR_WIDTH [31:0] $end
    $var wire 1 _ clk $end
    $var wire 10 ^ addr [9:0] $end
    $var wire 32 Y din [31:0] $end
    $var wire 1 K mem_read $end
    $var wire 1 L mem_write $end
    $var wire 32 c dout [31:0] $end
   $upscope $end
   $scope module u_imem_0 $end
    $var wire 32 f IMEM_DEPTH [31:0] $end
    $var wire 32 g IMEM_ADDR_WIDTH [31:0] $end
    $var wire 10 D addr [9:0] $end
    $var wire 32 E dout [31:0] $end
    $scope module unnamedblk1 $end
     $var wire 32 # i [31:0] $end
    $upscope $end
   $upscope $end
   $scope module u_regfile_0 $end
    $var wire 32 h REG_WIDTH [31:0] $end
    $var wire 1 _ clk $end
    $var wire 5 F rs1 [4:0] $end
    $var wire 5 G rs2 [4:0] $end
    $var wire 5 H rd [4:0] $end
    $var wire 32 a rd_din [31:0] $end
    $var wire 1 I reg_write $end
    $var wire 32 b rs1_dout [31:0] $end
    $var wire 32 Y rs2_dout [31:0] $end
    $var wire 32 $ rf_data[0] [31:0] $end
    $var wire 32 % rf_data[1] [31:0] $end
    $var wire 32 & rf_data[2] [31:0] $end
    $var wire 32 ' rf_data[3] [31:0] $end
    $var wire 32 ( rf_data[4] [31:0] $end
    $var wire 32 ) rf_data[5] [31:0] $end
    $var wire 32 * rf_data[6] [31:0] $end
    $var wire 32 + rf_data[7] [31:0] $end
    $var wire 32 , rf_data[8] [31:0] $end
    $var wire 32 - rf_data[9] [31:0] $end
    $var wire 32 . rf_data[10] [31:0] $end
    $var wire 32 / rf_data[11] [31:0] $end
    $var wire 32 0 rf_data[12] [31:0] $end
    $var wire 32 1 rf_data[13] [31:0] $end
    $var wire 32 2 rf_data[14] [31:0] $end
    $var wire 32 3 rf_data[15] [31:0] $end
    $var wire 32 4 rf_data[16] [31:0] $end
    $var wire 32 5 rf_data[17] [31:0] $end
    $var wire 32 6 rf_data[18] [31:0] $end
    $var wire 32 7 rf_data[19] [31:0] $end
    $var wire 32 8 rf_data[20] [31:0] $end
    $var wire 32 9 rf_data[21] [31:0] $end
    $var wire 32 : rf_data[22] [31:0] $end
    $var wire 32 ; rf_data[23] [31:0] $end
    $var wire 32 < rf_data[24] [31:0] $end
    $var wire 32 = rf_data[25] [31:0] $end
    $var wire 32 > rf_data[26] [31:0] $end
    $var wire 32 ? rf_data[27] [31:0] $end
    $var wire 32 @ rf_data[28] [31:0] $end
    $var wire 32 A rf_data[29] [31:0] $end
    $var wire 32 B rf_data[30] [31:0] $end
    $var wire 32 C rf_data[31] [31:0] $end
   $upscope $end
  $upscope $end
 $upscope $end
$enddefinitions $end


#0
b00000000000000000000010000000000 #
b00000000000000000000000000000000 $
b00000000000000000000000000000000 %
b00000000000000000000000000000000 &
b00000000000000000000000000000000 '
b00000000000000000000000000000000 (
b00000000000000000000000000000000 )
b00000000000000000000000000000000 *
b00000000000000000000000000000000 +
b00000000000000000000000000000000 ,
b00000000000000000000000000000000 -
b00000000000000000000000000000000 .
b00000000000000000000000000000000 /
b00000000000000000000000000000000 0
b00000000000000000000000000000000 1
b00000000000000000000000000000000 2
b00000000000000000000000000000000 3
b00000000000000000000000000000000 4
b00000000000000000000000000000000 5
b00000000000000000000000000000000 6
b00000000000000000000000000000000 7
b00000000000000000000000000000000 8
b00000000000000000000000000000000 9
b00000000000000000000000000000000 :
b00000000000000000000000000000000 ;
b00000000000000000000000000000000 <
b00000000000000000000000000000000 =
b00000000000000000000000000000000 >
b00000000000000000000000000000000 ?
b00000000000000000000000000000000 @
b00000000000000000000000000000000 A
b00000000000000000000000000000000 B
b00000000000000000000000000000000 C
b0000000000 D
b00000000000000000010001000000011 E
b00000 F
b00000 G
b00100 H
1I
b0010 J
1K
0L
b0000011 M
b0000 N
1O
b00 P
b010 Q
b0000000 R
b00000000000000000000000000000000 S
b00000000000000000000000000000000 T
b000000000000 U
b00000000000000000000000000000000 V
b00000000000000000000000000000100 W
b00000000000000000000000000000000 X
b00000000000000000000000000000000 Y
b00000000000000000000000000000000 Z
b00000000000000000000000000000000 [
1\
0]
b0000000000 ^
0_
0`
b00000000000000000000000011111111 a
b00000000000000000000000000000000 b
b00000000000000000000000011111111 c
b00000000000000000000000000000100 d
0e
b00000000000000000000010000000000 f
b00000000000000000000000000001010 g
b00000000000000000000000000100000 h
#5
b00000000000000000000000011111111 (
1_
#10
0_
#15
b0000000001 D
b00000000100000000010001010000011 E
b01000 G
b00101 H
b00000000000000000000000000001000 S
b00000000000000000000000000010000 T
b000000001000 U
b00000000000000000000000000000100 V
b00000000000000000000000000001000 W
b00000000000000000000000000010100 X
b00000000000000000000000000001000 Z
b00000000000000000000000000001000 [
0\
b0000000010 ^
1_
1`
b00000000000000000000000000000010 a
b00000000000000000000000000000010 c
b00000000000000000000000000001000 d
#20
0_
#25
b00000000000000000000000000000010 )
b0000000010 D
b00000001000000000010001100000011 E
b10000 G
b00110 H
b00000000000000000000000000010000 S
b00000000000000000000000000100000 T
b000000010000 U
b00000000000000000000000000001000 V
b00000000000000000000000000001100 W
b00000000000000000000000000101000 X
b00000000000000000000000000010000 Z
b00000000000000000000000000010000 [
b0000000100 ^
1_
b00000000000000000000000000000100 a
b00000000000000000000000000000100 c
b00000000000000000000000000001100 d
#30
0_
#35
b00000000000000000000000000000100 *
b0000000011 D
b00000000010000101000001110110011 E
b00101 F
b00100 G
b00111 H
0K
b0110011 M
0O
b10 P
b000 Q
b00000000000000000000000000000000 S
b00000000000000000000000000000000 T
b000000000000 U
b00000000000000000000000000001100 V
b00000000000000000000000000010000 W
b00000000000000000000000000001100 X
b00000000000000000000000011111111 Y
b00000000000000000000000011111111 Z
b00000000000000000000000100000001 [
b0001000000 ^
1_
b00000000000000000000000100000001 a
b00000000000000000000000000000010 b
b00000000000000000000000000000000 c
b00000000000000000000000000010000 d
#40
0_
#45
b00000000000000000000000100000001 +
b0000000100 D
b01000000010000101000010000110011 E
b01000 H
b0110 J
b0100000 R
b00000000000000000000000000010000 V
b00000000000000000000000000010100 W
b00000000000000000000000000010000 X
b11111111111111111111111100000011 [
1]
b1111000000 ^
1_
b11111111111111111111111100000011 a
b00000000000000000000000000010100 d
#50
0_
#55
b11111111111111111111111100000011 ,
b0000000101 D
b00000000010000101111010010110011 E
b01001 H
b0000 J
b111 Q
b0000000 R
b00000000000000000000000000010100 V
b00000000000000000000000000011000 W
b00000000000000000000000000010100 X
b00000000000000000000000000000010 [
0]
b0000000000 ^
1_
b00000000000000000000000000000010 a
b00000000000000000000000000011000 d
#60
0_
#65
b00000000000000000000000000000010 -
b0000000110 D
b00000000010000101110010100110011 E
b01010 H
b0001 J
b110 Q
b00000000000000000000000000011000 V
b00000000000000000000000000011100 W
b00000000000000000000000000011000 X
b00000000000000000000000011111111 [
b0000111111 ^
1_
b00000000000000000000000011111111 a
b00000000000000000000000000011100 d
#70
0_
#75
b00000000000000000000000011111111 .
b0000000111 D
b00000000010000101100010110110011 E
b01011 H
b0011 J
b100 Q
b00000000000000000000000000011100 V
b00000000000000000000000000100000 W
b00000000000000000000000000011100 X
b00000000000000000000000011111101 [
1_
b00000000000000000000000011111101 a
b00000000000000000000000000100000 d
#80
0_
#85
b00000000000000000000000011111101 /
b0000001000 D
b00000000000100100000110110010011 E
b00100 F
b00001 G
b11011 H
b0010 J
b0010011 M
1O
b000 Q
b00000000000000000000000000000001 S
b00000000000000000000000000000010 T
b000000000001 U
b00000000000000000000000000100000 V
b00000000000000000000000000100100 W
b00000000000000000000000000100010 X
b00000000000000000000000000000000 Y
b00000000000000000000000000000001 Z
b00000000000000000000000100000000 [
b0001000000 ^
1_
b00000000000000000000000100000000 a
b00000000000000000000000011111111 b
b00000000000000000000000000100100 d
#90
0_
#95
b00000000000000000000000100000000 ?
b0000001001 D
b11111111100100100000111000010011 E
b11001 G
b11100 H
b1111111 R
b11111111111111111111111111111001 S
b11111111111111111111111111110010 T
b111111111001 U
b00000000000000000000000000100100 V
b00000000000000000000000000101000 W
b00000000000000000000000000010110 X
b11111111111111111111111111111001 Z
b00000000000000000000000011111000 [
b0000111110 ^
1_
b00000000000000000000000011111000 a
b00000000000000000000000000101000 d
#100
0_
#105
b00000000000000000000000011111000 @
b0000001010 D
b00000000111100100111111010010011 E
b01111 G
b11101 H
b0000 J
b111 Q
b0000000 R
b00000000000000000000000000001111 S
b00000000000000000000000000011110 T
b000000001111 U
b00000000000000000000000000101000 V
b00000000000000000000000000101100 W
b00000000000000000000000001000110 X
b00000000000000000000000000001111 Z
b00000000000000000000000000001111 [
b0000000011 ^
1_
b00000000000000000000000000001111 a
b00000000000000000000000000101100 d
#110
0_
#115
b00000000000000000000000000001111 A
b0000001011 D
b00000001000000100110111100010011 E
b10000 G
b11110 H
b0001 J
b110 Q
b00000000000000000000000000010000 S
b00000000000000000000000000100000 T
b000000010000 U
b00000000000000000000000000101100 V
b00000000000000000000000000110000 W
b00000000000000000000000001001100 X
b00000000000000000000000000010000 Z
b00000000000000000000000011111111 [
b0000111111 ^
1_
b00000000000000000000000011111111 a
b00000000000000000000000000110000 d
#120
0_
#125
b00000000000000000000000011111111 B
b0000001100 D
b00000000111100100100111110010011 E
b01111 G
b11111 H
b0011 J
b100 Q
b00000000000000000000000000001111 S
b00000000000000000000000000011110 T
b000000001111 U
b00000000000000000000000000110000 V
b00000000000000000000000000110100 W
b00000000000000000000000001001110 X
b00000000000000000000000000001111 Z
b00000000000000000000000011110000 [
b0000111100 ^
1_
b00000000000000000000000011110000 a
b00000000000000000000000000110100 d
#130
0_
#135
b00000000000000000000000011110000 C
b0000001101 D
b11111100100000111000110011100011 E
b00111 F
b01000 G
b11001 H
0I
b0110 J
b1100011 M
b0001 N
0O
b01 P
b000 Q
b1111110 R
b11111111111111111111111111101100 S
b11111111111111111111111111011000 T
b111111101100 U
b00000000000000000000000000110100 V
b00000000000000000000000000111000 W
b00000000000000000000000000001100 X
b11111111111111111111111100000011 Y
b11111111111111111111111100000011 Z
b00000000000000000000000111111110 [
b0001111111 ^
1_
b00000000000000000000000111111110 a
b00000000000000000000000100000001 b
b00000000000000000000000000111000 d
#140
0_
#145
b0000001110 D
b00000000011100000010110000100011 E
b00000 F
b00111 G
b11000 H
b0010 J
1L
b0100011 M
b0000 N
1O
b00 P
b010 Q
b0000000 R
b00000000000000000000000000011000 S
b00000000000000000000000000110000 T
b000000011000 U
b00000000000000000000000000111000 V
b00000000000000000000000000111100 W
b00000000000000000000000001101000 X
b00000000000000000000000100000001 Y
b00000000000000000000000000011000 Z
b00000000000000000000000000011000 [
b0000000110 ^
1_
b00000000000000000000000000011000 a
b00000000000000000000000000000000 b
b00000000000000000000000000111100 d
#150
0_
#155
b0000001111 D
b00000001100000000010010110000011 E
b11000 G
b01011 H
1I
1K
0L
b0000011 M
b00000000000000000000000000111100 V
b00000000000000000000000001000000 W
b00000000000000000000000001101100 X
b00000000000000000000000000000000 Y
1_
b00000000000000000000000100000001 a
b00000000000000000000000100000001 c
b00000000000000000000000001000000 d
#160
0_
#165
b00000000000000000000000100000001 /
b0000010000 D
b11111100101100111001011011100011 E
b00111 F
b01011 G
b01101 H
0I
b0110 J
0K
b1100011 M
b0010 N
0O
b01 P
b001 Q
b1111110 R
b11111111111111111111111111100110 S
b11111111111111111111111111001100 T
b111111100110 U
b00000000000000000000000001000000 V
b00000000000000000000000001000100 W
b00000000000000000000000000001100 X
b00000000000000000000000100000001 Y
b00000000000000000000000100000001 Z
b00000000000000000000000000000000 [
1\
b0000000000 ^
1_
b00000000000000000000000000000000 a
b00000000000000000000000100000001 b
b00000000000000000000000000000000 c
b00000000000000000000000001000100 d
#170
0_
#175
b0000010001 D
b00000010000000000010001000000011 E
b00000 F
b00000 G
b00100 H
1I
b0010 J
1K
b0000011 M
b0000 N
1O
b00 P
b010 Q
b0000001 R
b00000000000000000000000000100000 S
b00000000000000000000000001000000 T
b000000100000 U
b00000000000000000000000001000100 V
b00000000000000000000000001001000 W
b00000000000000000000000010000100 X
b00000000000000000000000000000000 Y
b00000000000000000000000000100000 Z
b00000000000000000000000000100000 [
0\
b0000001000 ^
1_
b00000000000000000000000000001000 a
b00000000000000000000000000000000 b
b00000000000000000000000000001000 c
b00000000000000000000000001001000 d
#180
0_
#185
b00000000000000000000000000001000 (
b0000010010 D
b00000010100000000010001010000011 E
b01000 G
b00101 H
b00000000000000000000000000101000 S
b00000000000000000000000001010000 T
b000000101000 U
b00000000000000000000000001001000 V
b00000000000000000000000001001100 W
b00000000000000000000000010011000 X
b11111111111111111111111100000011 Y
b00000000000000000000000000101000 Z
b00000000000000000000000000101000 [
b0000001010 ^
1_
b00000000000000000000000000000000 a
b00000000000000000000000000000000 c
b00000000000000000000000001001100 d
#190
0_
#195
b00000000000000000000000000000000 )
b0000010011 D
b11111110010100100101110011100011 E
b00100 F
b00101 G
b11001 H
0I
b0110 J
0K
b1100011 M
b1000 N
0O
b01 P
b101 Q
b1111111 R
b11111111111111111111111111111100 S
b11111111111111111111111111111000 T
b111111111100 U
b00000000000000000000000001001100 V
b00000000000000000000000001010000 W
b00000000000000000000000001000100 X
b00000000000000000000000000000000 Y
b00000000000000000000000000000000 Z
b00000000000000000000000000001000 [
b0000000010 ^
1_
b00000000000000000000000000001000 a
b00000000000000000000000000001000 b
b00000000000000000000000001000100 d
1e
#200
0_
#205
b0000010001 D
b00000010000000000010001000000011 E
b00000 F
b00000 G
b00100 H
1I
b0010 J
1K
b0000011 M
b0000 N
1O
b00 P
b010 Q
b0000001 R
b00000000000000000000000000100000 S
b00000000000000000000000001000000 T
b000000100000 U
b00000000000000000000000001000100 V
b00000000000000000000000001001000 W
b00000000000000000000000010000100 X
b00000000000000000000000000100000 Z
b00000000000000000000000000100000 [
b0000001000 ^
1_
b00000000000000000000000000000000 b
b00000000000000000000000000001000 c
b00000000000000000000000001001000 d
0e
#210
0_
#215
b0000010010 D
b00000010100000000010001010000011 E
b01000 G
b00101 H
b00000000000000000000000000101000 S
b00000000000000000000000001010000 T
b000000101000 U
b00000000000000000000000001001000 V
b00000000000000000000000001001100 W
b00000000000000000000000010011000 X
b11111111111111111111111100000011 Y
b00000000000000000000000000101000 Z
b00000000000000000000000000101000 [
b0000001010 ^
1_
b00000000000000000000000000000000 a
b00000000000000000000000000000000 c
b00000000000000000000000001001100 d
#220
0_
#225
b0000010011 D
b11111110010100100101110011100011 E
b00100 F
b00101 G
b11001 H
0I
b0110 J
0K
b1100011 M
b1000 N
0O
b01 P
b101 Q
b1111111 R
b11111111111111111111111111111100 S
b11111111111111111111111111111000 T
b111111111100 U
b00000000000000000000000001001100 V
b00000000000000000000000001010000 W
b00000000000000000000000001000100 X
b00000000000000000000000000000000 Y
b00000000000000000000000000000000 Z
b00000000000000000000000000001000 [
b0000000010 ^
1_
b00000000000000000000000000001000 a
b00000000000000000000000000001000 b
b00000000000000000000000001000100 d
1e
#230
0_
#235
b0000010001 D
b00000010000000000010001000000011 E
b00000 F
b00000 G
b00100 H
1I
b0010 J
1K
b0000011 M
b0000 N
1O
b00 P
b010 Q
b0000001 R
b00000000000000000000000000100000 S
b00000000000000000000000001000000 T
b000000100000 U
b00000000000000000000000001000100 V
b00000000000000000000000001001000 W
b00000000000000000000000010000100 X
b00000000000000000000000000100000 Z
b00000000000000000000000000100000 [
b0000001000 ^
1_
b00000000000000000000000000000000 b
b00000000000000000000000000001000 c
b00000000000000000000000001001000 d
0e
#240
0_
