Lab3/imem/imem.sv
/* ********************************************
 *	COSE222 Lab #3
 *
 *	Module: instruction memory (imem.sv)
 *	- 1 address input port
 *	- 32-bit 1 data output port
 *	- A single entry size is 32 bit, which is equivalent to the RISC-V instruction size
 *
 *	Author: Gunjae Koo (gunjaekoo@korea.ac.kr)
 *
 * ********************************************
 */

`timescale 1ns/1ps

module imem
#(  parameter IMEM_DEPTH = 1024,    // imem depth (default: 1024 entries = 4 KB)
              IMEM_ADDR_WIDTH = 10 )
(
    input   [IMEM_ADDR_WIDTH-1:0]   addr,
    output  [31:0]  dout
);

    logic[31:0] data[0:IMEM_DEPTH-1];
    assign dout = data[addr];

// synthesis translate_off
    initial begin
        for (int i = 0; i < IMEM_DEPTH; i++)
            data[i] = i*2;
        //$readmemb("imem.mem", data);
    end
// synthesis translate_on
endmodule

Lab3/imem/wave.vcd
$version Generated by VerilatedVcd $end
$timescale 1ps $end
 $scope module TOP $end
  $var wire 10 $ addr [9:0] $end
  $var wire 32 % dout [31:0] $end
  $scope module imem $end
   $var wire 32 & IMEM_DEPTH [31:0] $end
   $var wire 32 ' IMEM_ADDR_WIDTH [31:0] $end
   $var wire 10 $ addr [9:0] $end
   $var wire 32 % dout [31:0] $end
   $scope module unnamedblk1 $end
    $var wire 32 # i [31:0] $end
   $upscope $end
  $upscope $end
 $upscope $end
$enddefinitions $end


#0
b00000000000000000000010000000000 #
b0000000000 $
b00000000000000000000000000000000 %
b00000000000000000000010000000000 &
b00000000000000000000000000001010 '
#5
#10
#15
#20
#25
b0000000001 $
b00000000000000000000000000000010 %
#30
#35
b0000000010 $
b00000000000000000000000000000100 %
#40
#45
b0000000011 $
b00000000000000000000000000000110 %
#50
#55
b0000000100 $
b00000000000000000000000000001000 %
#60
#65
b0000000101 $
b00000000000000000000000000001010 %
#70
#75
b0000000110 $
b00000000000000000000000000001100 %
#80
#85
b0000000111 $
b00000000000000000000000000001110 %
#90
#95
b0000001000 $
b00000000000000000000000000010000 %
#100
#105
b0000001001 $
b00000000000000000000000000010010 %
#110
#115
b0000001010 $
b00000000000000000000000000010100 %
#120
#125
b0000001011 $
b00000000000000000000000000010110 %
#130
#135
b0000001100 $
b00000000000000000000000000011000 %
#140
#145
b0000001101 $
b00000000000000000000000000011010 %
#150
#155
b0000001110 $
b00000000000000000000000000011100 %
#160
#165
b0000001111 $
b00000000000000000000000000011110 %
#170
#175
b0000010000 $
b00000000000000000000000000100000 %
#180
#185
b0000010001 $
b00000000000000000000000000100010 %
#190
#195
b0000010010 $
b00000000000000000000000000100100 %
